nelogopy/__init__.py
nelogopy/nelogopy.nlogo
nelogopy/nelogopy.py
nelogopy-0.0.14.data/data/netlogo/nelogopy.nlogo
nelogopy-0.0.14.dist-info/LICENSE
nelogopy-0.0.14.dist-info/METADATA
nelogopy-0.0.14.dist-info/WHEEL
nelogopy-0.0.14.dist-info/top_level.txt
nelogopy-0.0.14.dist-info/RECORD
