Metadata-Version: 2.1
Name: nelogopy
Version: 0.0.14
Summary: nelogopy : Usage netlogo by python
Author: BOUAZIZ (BOUAZIZ NOURDDINE)
Author-email: <nourddine.bouaziz.dz@gmail.com>
Keywords: python,netlogo,simulation,multi agent
Classifier: Development Status :: 1 - Planning
Classifier: Intended Audience :: Developers
Classifier: Programming Language :: Python :: 3
Classifier: Operating System :: Unix
Classifier: Operating System :: MacOS :: MacOS X
Classifier: Operating System :: Microsoft :: Windows
License-File: LICENSE
Requires-Dist: nl4py
